edurov/__init__.py
edurov/core.py
edurov/keys.txt
edurov/sync.py
edurov/utils.py
edurov/web.py
edurov-0.0.5.dist-info/DESCRIPTION.rst
edurov-0.0.5.dist-info/METADATA
edurov-0.0.5.dist-info/RECORD
edurov-0.0.5.dist-info/WHEEL
edurov-0.0.5.dist-info/entry_points.txt
edurov-0.0.5.dist-info/metadata.json
edurov-0.0.5.dist-info/top_level.txt
examples/__init__.py
examples/edurov_web/Readme.rst
examples/edurov_web/__init__.py
examples/edurov_web/entry.py
examples/edurov_web/favicon.ico
examples/edurov_web/index.html
examples/edurov_web/start.py
examples/edurov_web/static/bootstrap.css
examples/edurov_web/static/dynamic.js
examples/edurov_web/static/general.js
examples/edurov_web/static/keys.js
examples/edurov_web/static/roll.png
examples/edurov_web/static/style.css
