Metadata-Version: 2.0
Name: edurov
Version: 0.0.5
Summary: A educational project for remotely operated vehicles
Home-page: https://github.com/trolllabs/eduROV
Author: trolllabs
Author-email: martinloland@gmail.com
License: GPLv3
Project-URL: Documentation, http://edurov.readthedocs.io
Project-URL: Source, https://github.com/trolllabs/eduROV/
Project-URL: Tracker, https://github.com/trolllabs/eduROV/issues
Keywords: video education ROV picamera
Platform: UNKNOWN
Classifier: Development Status :: 5 - Production/Stable
Classifier: Intended Audience :: Education
Classifier: Intended Audience :: End Users/Desktop
Classifier: Topic :: Education
Classifier: Topic :: Internet :: WWW/HTTP
Classifier: Topic :: Multimedia :: Video :: Display
Classifier: Framework :: Robot Framework
Classifier: License :: OSI Approved :: GNU General Public License v3 (GPLv3)
Classifier: Programming Language :: Python :: 3
Requires-Python: >=3
Requires-Dist: Pyro4
Requires-Dist: picamera (==1.13)
